mechtest_ufmg/Properties.py
mechtest_ufmg/Tensile_properties.py
mechtest_ufmg/Utils.py
mechtest_ufmg/__init__.py
mechtest_ufmg-0.1.2.dist-info/LICENSE
mechtest_ufmg-0.1.2.dist-info/METADATA
mechtest_ufmg-0.1.2.dist-info/WHEEL
mechtest_ufmg-0.1.2.dist-info/top_level.txt
mechtest_ufmg-0.1.2.dist-info/RECORD
