Metadata-Version: 2.1
Name: mechtest-ufmg
Version: 0.1.2
Summary: Performs calculations on tensile test results for lectures at UFMG
Home-page: https://github.com/pedrodamas0803/tensile_test
Author: Pedro D. Resende
Author-email: pdrodresende@gmail.com
License: MIT
Platform: UNKNOWN
